vidtoolz_apply_greenscreen/__init__.py
vidtoolz_apply_greenscreen/apply_greenscreen.py
vidtoolz_apply_greenscreen-0.0.1.dist-info/LICENSE
vidtoolz_apply_greenscreen-0.0.1.dist-info/METADATA
vidtoolz_apply_greenscreen-0.0.1.dist-info/WHEEL
vidtoolz_apply_greenscreen-0.0.1.dist-info/entry_points.txt
vidtoolz_apply_greenscreen-0.0.1.dist-info/top_level.txt
vidtoolz_apply_greenscreen-0.0.1.dist-info/RECORD
