Metadata-Version: 2.2
Name: vidtoolz-apply-greenscreen
Version: 0.0.1
Summary: Apply greenscreen video on top of a video
Author: Sukhbinder Singh
License: Apache-2.0
Project-URL: Homepage, https://github.com/sukhbinder/vidtoolz-apply-greenscreen
Project-URL: Changelog, https://github.com/sukhbinder/vidtoolz-apply-greenscreen/releases
Project-URL: Issues, https://github.com/sukhbinder/vidtoolz-apply-greenscreen/issues
Project-URL: CI, https://github.com/sukhbinder/vidtoolz-apply-greenscreen/actions
Classifier: License :: OSI Approved :: Apache Software License
License-File: LICENSE
Requires-Dist: vidtoolz
Requires-Dist: numpy
Provides-Extra: test
Requires-Dist: pytest; extra == "test"
